fastpluggy_plugin/redis_tools/__init__.py
fastpluggy_plugin/redis_tools/config.py
fastpluggy_plugin/redis_tools/plugin.py
fastpluggy_plugin/redis_tools/redis_connector.py
fastpluggy_plugin/redis_tools/router.py
fastpluggy_plugin/redis_tools/schema.py
fastpluggy_plugin/redis_tools/stats_card_tools.py
fastpluggy_plugin/redis_tools/tasks/__init__.py
fastpluggy_plugin/redis_tools/tasks/purge.py
fastpluggy_plugin/redis_tools/templates/browser.html.j2
fastpluggy_plugin/redis_tools/templates/raw_command.html.j2
fastpluggy_redis-0.0.20.dist-info/METADATA
fastpluggy_redis-0.0.20.dist-info/WHEEL
fastpluggy_redis-0.0.20.dist-info/entry_points.txt
fastpluggy_redis-0.0.20.dist-info/top_level.txt
fastpluggy_redis-0.0.20.dist-info/RECORD
