Metadata-Version: 2.4
Name: fastpluggy-redis
Version: 0.0.20
Summary: Redis Tools plugin for Fastpluggy
Author: FastPluggy Team
Requires-Python: >=3.10
Requires-Dist: redis
Requires-Dist: fastpluggy-ui-tools>=0.0.4
